wagtail_multiple_chooser_panel/__init__.py
wagtail_multiple_chooser_panel/apps.py
wagtail_multiple_chooser_panel/models.py
wagtail_multiple_chooser_panel/panels.py
wagtail_multiple_chooser_panel/migrations/__init__.py
wagtail_multiple_chooser_panel/static/wagtail_multiple_chooser_panel/js/.gitignore
wagtail_multiple_chooser_panel/static/wagtail_multiple_chooser_panel/js/wagtail-multiple-chooser-panel.js
wagtail_multiple_chooser_panel/static_src/ExpandingFormset.js
wagtail_multiple_chooser_panel/static_src/InlinePanel.js
wagtail_multiple_chooser_panel/static_src/main.js
wagtail_multiple_chooser_panel/static_src/panels.ts
wagtail_multiple_chooser_panel/templates/wagtail_multiple_chooser_panel/multiple_chooser_panel.html
wagtail_multiple_chooser_panel/test/__init__.py
wagtail_multiple_chooser_panel/test/apps.py
wagtail_multiple_chooser_panel/test/settings.py
wagtail_multiple_chooser_panel/test/urls.py
wagtail_multiple_chooser_panel/test/tests/__init__.py
wagtail_multiple_chooser_panel-0.1.0.dist-info/LICENSE
wagtail_multiple_chooser_panel-0.1.0.dist-info/METADATA
wagtail_multiple_chooser_panel-0.1.0.dist-info/WHEEL
wagtail_multiple_chooser_panel-0.1.0.dist-info/top_level.txt
wagtail_multiple_chooser_panel-0.1.0.dist-info/RECORD
