Metadata-Version: 2.1
Name: wagtail-multiple-chooser-panel
Version: 0.1.0
Summary: An InlinePanel variant allowing multiple items to be quickly selected
Home-page: UNKNOWN
Author: Matt Westcott
Author-email: matthew@torchbox.com
License: BSD
Platform: UNKNOWN
Classifier: Development Status :: 3 - Alpha
Classifier: Intended Audience :: Developers
Classifier: License :: OSI Approved :: BSD License
Classifier: Operating System :: OS Independent
Classifier: Programming Language :: Python
Classifier: Programming Language :: Python :: 3
Classifier: Programming Language :: Python :: 3.7
Classifier: Programming Language :: Python :: 3.8
Classifier: Programming Language :: Python :: 3.9
Classifier: Programming Language :: Python :: 3.10
Classifier: Programming Language :: Python :: 3.11
Classifier: Framework :: Django
Classifier: Framework :: Django :: 3.2
Classifier: Framework :: Django :: 4.0
Classifier: Framework :: Django :: 4.1
Classifier: Framework :: Wagtail
Classifier: Framework :: Wagtail :: 4
Requires-Dist: Django (<4.2,>=3.2)
Requires-Dist: Wagtail (<4.2,>=4.1)
Provides-Extra: testing
Requires-Dist: dj-database-url (==0.5.0) ; extra == 'testing'
Requires-Dist: freezegun (==0.3.15) ; extra == 'testing'
